LICENSE.txt
README.md
setup.cfg
setup.py
caretaker_f2.egg-info/PKG-INFO
caretaker_f2.egg-info/SOURCES.txt
caretaker_f2.egg-info/dependency_links.txt
caretaker_f2.egg-info/requires.txt
caretaker_f2.egg-info/top_level.txt
src/__init__.py
src/analysis.py
src/bar_chart.py
src/classify.py
src/crypto.py
src/dashboard_driver.py
src/data.py
src/data_driver.py
src/docopt_utility.py
src/finance_db.py
src/graph.py
src/pricing.py
src/questrade_2.py