Metadata-Version: 2.1
Name: caretaker-f2
Version: 1.0
Summary: finance management tool
Home-page: https://github.com/dn757657/caretaker_f2
Author: Dan
Author-email: daniel.js.campbell@gmail.com
License: MIT
Download-URL: https://github.com/dn757657/caretaker_f2/archive/refs/tags/testing.tar.gz
Keywords: Management,finance,automation
Platform: UNKNOWN
Classifier: Development Status :: 3 - Alpha
Classifier: Intended Audience :: Developers
Classifier: Topic :: Software Development :: Build Tools
Classifier: License :: OSI Approved :: MIT License
Classifier: Programming Language :: Python :: 3
Classifier: Programming Language :: Python :: 3.4
Classifier: Programming Language :: Python :: 3.5
Classifier: Programming Language :: Python :: 3.6
License-File: LICENSE.txt
